{
  "dashboard": "Tablero",
  "Users": "Usuarios",
  "Settings": "Configuración",
  "Action": "Acción",
  "Create your account": "Crear tu cuenta",
  "Customer": "Cliente",
  "Analyst": "Analista",
  "Select a Company": "Seleccione una compañia",
  "Another action": "Otra acción",
  "Something else here...": "Algo más aquí...",
  "Register": "Registro",
  "Disabled action": "Acción deshabilitada",
  "SignIn": "Iniciar Sesión",
  "Profile": "Profile",
  "Income": "Ingresos",
  "Conversion rate": "Tasa de Conversión",
  "Sessions": "Sesiones",
  "Crear Usuario": "Create User",
  "issues": "Problemas",
  "Password": "Contraseña",
  "New password": "Nueva Contraseña",
  "Confirm password": "Confirmar Contraseña",
  "Create Account": "Crear cuenta",
  "New": "Nuevo",
  "New issue": "Nuevo Problema",
  "Description": "Descripción",
  "Home": "Inicio",
  "Gestion": "Management",
  "Name": "Nombre",
  "Save changes": "Guardar Cambios",
  "Dashboard": "Tablero",
  "Light": "Luz",
  "Dark": "Oscuro",
  "Auto": "Auto",
  "Close": "Cerrar",
  "Enter issue name": "Ingrese el nombre del Problema",
  "Enter issue description": "Ingrese la descripción del Problema"

}
